{
  "$schema": "https://docs.renovatebot.com/renovate-schema.json",
  "packageRules": [
    {
      "description": ["Auto-merge GitHub Actions for minor and patch"],
      "matchManagers": ["github-actions"],
      "matchDatasources": ["github-tags"],
      "automerge": true,
      "automergeType": "branch",
      "matchUpdateTypes": ["minor", "patch"]
    },
    {
      "description": ["Auto-merge specific apps' minor versions"],
      "automerge": true,
      "automergeType": "pr",
      "rebaseWhen": "behind-base-branch",
      "matchDatasources": ["docker", "helm"],
      "matchPackageNames": [
        "**/bazarr",
        "**/calibre-web-automated-book-downloader",
        "**/cloudflare-ddns",
        "**/code-server",
        "**/collabora",
        "**/coredns",
        "**/flaresolverr",
        "**/generic-device-plugin",
        "**/grafana",
        "**/it-tools",
        "**/k8s-sidecar",
        "**/kube-prometheus-stack",
        "**/loki",
        "**/meilisearch",
        "**/omni-tools",
        "**/open-webui",
        "**/prowlarr",
        "**/prometheus-smartctl-exporter",
        "**/radarr",
        "**/renovate",
        "**/searxng",
        "**/smartmontools",
        "**/sonarr",
        "**/zfs-scrubber"
      ],
      "matchUpdateTypes": ["minor", "patch", "digest"],
    },
    {
      "description": ["Auto-merge specific apps' major versions"],
      "automerge": true,
      "automergeType": "pr",
      "rebaseWhen": "behind-base-branch",
      "matchDatasources": ["docker", "helm"],
      "matchPackageNames": [
        "**/firefox",
        "**/http-https-echo",
      ],
      "matchUpdateTypes": ["major", "minor", "patch", "digest"],
    }
  ]
}
